{
  "medications.json" : {
    "questionType" : "MultipleChoice",
    "choiceAnswers" : "(\n    \"Bromocriptine (Parlodel)\"\n)",
    "startDate" : "2015-02-09 07:26:38 +0000",
    "endDate" : "2015-02-09 07:26:42 +0000",
    "item" : "medications"
  },
  "personal-relationships.json" : {
    "questionType" : "SingleChoice",
    "choiceAnswers" : "(\n    Occassionally\n)",
    "startDate" : "2015-02-09 07:26:47 +0000",
    "endDate" : "2015-02-09 07:26:51 +0000",
    "item" : "personal-relationships"
  },
  "info.json" : {
    "taskRun" : "5844509E-4380-4524-A5A1-058A6D94CFF3",
    "files" : [ {
      "contentType" : "application/json",
      "filename" : "medications-change.json",
      "timestamp" : "2015-02-09 07:26:38 +0000"
    }, {
      "contentType" : "application/json",
      "filename" : "medications.json",
      "timestamp" : "2015-02-09 07:26:42 +0000"
    }, {
      "contentType" : "application/json",
      "filename" : "moving.json",
      "timestamp" : "2015-02-09 07:26:44 +0000"
    }, {
      "contentType" : "application/json",
      "filename" : "dressing.json",
      "timestamp" : "2015-02-09 07:26:45 +0000"
    }, {
      "contentType" : "application/json",
      "filename" : "depressed.json",
      "timestamp" : "2015-02-09 07:26:47 +0000"
    }, {
      "contentType" : "application/json",
      "filename" : "personal-relationships.json",
      "timestamp" : "2015-02-09 07:26:51 +0000"
    }, {
      "contentType" : "application/json",
      "filename" : "concentration.json",
      "timestamp" : "2015-02-09 07:26:53 +0000"
    }, {
      "contentType" : "application/json",
      "filename" : "communication.json",
      "timestamp" : "2015-02-09 07:26:55 +0000"
    }, {
      "contentType" : "application/json",
      "filename" : "spasms.json",
      "timestamp" : "2015-02-09 07:26:57 +0000"
    }, {
      "contentType" : "application/json",
      "filename" : "public-embarrassment.json",
      "timestamp" : "2015-02-09 07:27:06 +0000"
    } ],
    "item" : "parkinson-monthly"
  },
  "depressed.json" : {
    "questionType" : "SingleChoice",
    "choiceAnswers" : "(\n    Always\n)",
    "startDate" : "2015-02-09 07:26:45 +0000",
    "endDate" : "2015-02-09 07:26:47 +0000",
    "item" : "depressed"
  },
  "dressing.json" : {
    "questionType" : "SingleChoice",
    "choiceAnswers" : "(\n    Often\n)",
    "startDate" : "2015-02-09 07:26:44 +0000",
    "endDate" : "2015-02-09 07:26:45 +0000",
    "item" : "dressing"
  },
  "spasms.json" : {
    "questionType" : "SingleChoice",
    "choiceAnswers" : "(\n    Often\n)",
    "startDate" : "2015-02-09 07:26:55 +0000",
    "endDate" : "2015-02-09 07:26:57 +0000",
    "item" : "spasms"
  },
  "medications-change.json" : {
    "questionType" : "SingleChoice",
    "choiceAnswers" : "(\n    false\n)",
    "startDate" : "2015-02-09 07:26:36 +0000",
    "endDate" : "2015-02-09 07:26:38 +0000",
    "item" : "medications-change"
  },
  "concentration.json" : {
    "questionType" : "SingleChoice",
    "choiceAnswers" : "(\n    Often\n)",
    "startDate" : "2015-02-09 07:26:51 +0000",
    "endDate" : "2015-02-09 07:26:53 +0000",
    "item" : "concentration"
  },
  "public-embarrassment.json" : {
    "questionType" : "SingleChoice",
    "choiceAnswers" : "(\n    Often\n)",
    "startDate" : "2015-02-09 07:26:57 +0000",
    "endDate" : "2015-02-09 07:27:06 +0000",
    "item" : "public-embarrassment"
  },
  "moving.json" : {
    "questionType" : "SingleChoice",
    "choiceAnswers" : "(\n    Often\n)",
    "startDate" : "2015-02-09 07:26:42 +0000",
    "endDate" : "2015-02-09 07:26:44 +0000",
    "item" : "moving"
  },
  "communication.json" : {
    "questionType" : "SingleChoice",
    "choiceAnswers" : "(\n    Sometimes\n)",
    "startDate" : "2015-02-09 07:26:53 +0000",
    "endDate" : "2015-02-09 07:26:55 +0000",
    "item" : "communication"
  }
}